Workbook

Sheet 分模块说明
B2: 序号 | C2: 模块 | D2: 模块功能 | E2: 内部逻辑文件(ILF) | F2: 外部接口文件（EIF） | G2: 外部输入(EI) | H2: 外部输出(EO) | I2: 外部查询(EQ) | J2: 未调整功能点数 | K2: 未调整功能规模 | L2: 含税小计（万元）
B3: 1 | C3: 时序数据采集增强中间件与基础平台服务 | D3: 提供A11增强采集所需的配置管理中心（采集频次/告警阈值/数据保留策略的集中配置与动态刷新）、MQTT消息中间件（支持QoS分级、Topic权限、双区消息同步）、边缘节点集群协同（百级分布式节点统一管理、指令下发、状态同步、日志汇聚）、RBAC权限管控（角色/岗位/数据行级细粒度访问控制）、全链路审计日志（采集-计算-存储各环节不可篡改日志）及系统健康自监控等基础平台能力，支撑高频时序数据在工控网-办公网双区架构下的安全稳定运行，为上层业务模块提供统一的环境底座。 | E3: 15 | F3: 0 | G3: 65 | H3: 8 | I3: 20 | J3: =10*E3+7*F3+4*G3+H3*5+4*I3 | K3: =SUMIF(功能点测算明细!C:C,C3,功能点测算明细!N:N) | L3: =K3*1.21*1.025*1773.33/10000
B4: 2 | C4: 油气生产设备物模型与测点标准化管理服务 | D4: 面向抽油机、螺杆泵、电潜泵、注水井、计量间等油气生产核心设备类型，建立标准化设备物模型体系（涵盖G1抽油机基础/G2电参数/G3变频/G4螺杆泵/G5潜油泵/G6组合/G7仪表扩展/G8变频扩展八大类模板），实现多厂商设备Modbus寄存器地址映射与融合接入，测点参数统一定义（测量类型/量程/精度/采集频次/告警阈值/数据单位），采集系数（斜率/偏移量）配置管理，动态基线自动计算与漂移检测，以及数据质量自动校验（量程校验/变化率校验/完整性校验/时效性校验），从源头保障采集数据的准确性和一致性。 | E4: 16 | F4: 0 | G4: 66 | H4: 8 | I4: 21 | J4: =10*E4+7*F4+4*G4+H4*5+4*I4 | K4: =SUMIF(功能点测算明细!C:C,C4,功能点测算明细!N:N) | L4: =K4*1.21*1.025*1773.33/10000
B5: 3 | C5: 多协议高频时序数据实时采集与异构设备统一接入服务 | D5: 提供Modbus RTU/TCP、OPC UA/DA、MQTT、HTTP等多工业协议的设备数据实时采集能力，兼容固定IP（直连采集）与动态IP（端口映射/反向代理穿透）两种网络环境，支持毫秒级至秒级高频采集与智能动态调频（异常自动提速至毫秒级/低谷自动降频节能/风暴时段错峰避让），针对A11当前未覆盖的工程器械监测、能源计量、安防等非A11设备源进行统一协议适配与接入，同时提供RTU状态感知（在线监测/故障识别/通道统计）、采集健康度日报（按设备统计实时在线率/数据完整率/通信成功率）及采集链路全路径追踪，有效弥补A11在异构数据源扩展接入上的不足。 | E5: 20 | F5: 1 | G5: 78 | H5: 10 | I5: 26 | J5: =10*E5+7*F5+4*G5+H5*5+4*I5 | K5: =SUMIF(功能点测算明细!C:C,C5,功能点测算明细!N:N) | L5: =K5*1.21*1.025*1773.33/10000
B6: 4 | C6: 边缘端前置流式计算与实时告警引擎服务 | D6: 将公式计算与告警判定逻辑从中心端数据库轮询模式升级为边缘端前置流式计算模式：在采用入库前流水计算架构——区别于传统采集-入库-轮询-告警模式（TDengine不堪重负、分钟级延迟），数据到达边缘节点后先经流式引擎逐条判定（告警/特征值/趋势标记），判定结果随原始数据一同写入时序库，告警在入库前完成、延迟毫秒级，彻底规避中心端数据库轮询压力。边缘节点对高频时序数据流进行实时计算（系统内置15种边缘流式计算算法：①滑窗特征算子层含均值、最值、标准差、趋势方向、变化速率等6种窗口聚合算子；②实时规则引擎层含阈值检测、突变检测、趋势检测、波动率检测、频次检测、滑动平均检测、变化率检测、波峰检测、连续异常检测、基线偏离检测、量程校验等9种判定算法，全算法在边缘节点内存内完成判定，单条规则判定延迟<1ms），在数据入库前完成告警判定与事件生成，有效降低中心端计算负载与告警响应时延（从分钟级降至秒级）。支持四级告警分级（Critical/Error/Warning/Info）及差异化响应策略（电话/短信/APP推送/系统弹窗），提供告警升级闭环管理（超时未响应自动升级），结合历史趋势分析实现告警规则的动态优化。支持通过可视化规则编排界面配置复杂业务逻辑，降低告警规则维护门槛。 | E6: 18 | F6: 1 | G6: 70 | H6: 9 | I6: 23 | J6: =10*E6+7*F6+4*G6+H6*5+4*I6 | K6: =SUMIF(功能点测算明细!C:C,C6,功能点测算明细!N:N) | L6: =K6*1.21*1.025*1773.33/10000
B7: 5 | C7: 设备资产全生命周期数据治理与运行健康评估服务 | D7: 以设备A2/A5标识为数据组织纽带，建立从设备注册、运行监测、维护保养到退役的全生命周期数据管理体系，构建"油田→作业区→站库→井组→单设备"五级资产层级树并与物模型深度绑定。融合高频时序运行数据、告警历史、设备台账及维护记录，按设备维度统一汇聚与查询，计算设备健康度评分（在线率/采集成功率/告警频次/数据完整率等），支持按设备类型、作业区域进行横纵向对比分析。提供覆盖数据采集→传输→计算→存储全环节的不可篡改操作轨迹记录，实现任意时刻数据状态的精确追溯。 | E7: 18 | F7: 1 | G7: 72 | H7: 9 | I7: 24 | J7: =10*E7+7*F7+4*G7+H7*5+4*I7 | K7: =SUMIF(功能点测算明细!C:C,C7,功能点测算明细!N:N) | L7: =K7*1.21*1.025*1773.33/10000
B8: 6 | C8: 高频时序数据分级存储与全链路安全管控服务 | D8: 基于国产化全栈环境（麒麟/统信UOS操作系统+国产CPU架构），采用TDengine时序数据库与关系型数据库结合的三级存储策略（SSD热数据0-30天/HDD温数据31天-1年/归档冷数据1年以上），支持按设备标识（A2/A5 ID）直接定位与快速检索任意测点的历史数据。提供全链路安全管控：采集端数据加密与认证、MQTT通道TLS加密、API接口HTTPS加密、存储端数据加密，结合细粒度权限控制（数据行级/API端点级/菜单级）和防篡改审计日志，确保数据在工控网-办公网跨区传输与存储全过程的合规性与安全性。提供数据备份恢复与异地容灾机制。 | E8: 16 | F8: 1 | G8: 62 | H8: 7 | I8: 19 | J8: =10*E8+7*F8+4*G8+H8*5+4*I8 | K8: =SUMIF(功能点测算明细!C:C,C8,功能点测算明细!N:N) | L8: =K8*1.21*1.025*1773.33/10000
B9: 7 | C9: 油气生产运行综合监控与多维数据分析看板服务 | D9: 提供涵盖设备运行状态总览、采集通道健康度监控、告警分布态势、公式计算实时状态（含寄存器换算公式Y=kX+b执行成功率、边缘流式15种算法规则命中率、派生计算公式P=UI√3等电气参数实时计算结果）等多维度的综合监控大盘组态配置与个性化仪表盘定制。实现告警→设备→采集链路的联动钻取分析（从告警卡片一键下钻至设备详情与原始数据），按日/周/月自动生成设备运行报告、采集质量统计报告与告警分析报告，支持GIS地图下钻（油田→作业区→站库→井组），弥补A11系统在综合监控可视化方面的不足。支持日报/周报/月报自动生成与推送。 | E9: 14 | F9: 0 | G9: 58 | H9: 8 | I9: 16 | J9: =10*E9+7*F9+4*G9+H9*5+4*I9 | K9: =SUMIF(功能点测算明细!C:C,C9,功能点测算明细!N:N) | L9: =K9*1.21*1.025*1773.33/10000
B10: 8 | C10: 高频时序数据全链路压力测试与性能验证服务 | D10: 针对本项目大规模设备接入（覆盖100余个作业区、单作业区1万设备点位、总计百万级测点）与海量时序数据节点（百万级数据点/秒吞吐）的高并发场景，提供从单业务功能验证到全链路协同压测的多阶段性能测试方案。通过边缘中枢模拟100+作业区百万级测点并发接入，每秒百万级数据点的写入压力，对CPU负载、内存占用、磁盘I/O吞吐、数据读写速度、消息传输延迟、压缩存储效率、并发连接数等关键性能指标进行极限测试；模拟断网重连、通道超时、设备异常离线、数据风暴等故障场景，验证系统的容错降级与自动恢复能力。测试覆盖数据采集→传输→公式计算→告警判定→数据存储→可视化查询的完整业务链路，支持单节点5个以上并发测试、7×24小时连续15天长稳测试，生成含性能基线、瓶颈定位与优化建议的完整报告。验证单节点在百百万级测点并发采集、10万QPS数据写入吞吐、<1ms规则判定延迟等极限压力下的系统稳定性，提供CPU利用率≤80%、内存占用≤70%、磁盘IOPS≥5000、端到端采集延迟≤50ms的量化性能基准 | E10: 8 | F10: 1 | G10: 26 | H10: 4 | I10: 3 | J10: =10*E10+7*F10+4*G10+H10*5+4*I10 | K10: =SUMIF(功能点测算明细!C:C,C10,功能点测算明细!N:N) | L10: =K10*1.21*1.025*1773.33/10000
B11: 合计 | E11: =SUM(E3:E10) | F11: =SUM(F3:F10) | G11: =SUM(G3:G10) | H11: =SUM(H3:H10) | I11: =SUM(I3:I10) | J11: =SUM(J3:J10) | K11: =SUM(K3:K10) | L11: =SUM(L3:L10)

Sheet 费用测算明细
B2: 软件定制开发费用估算 | I2: 测算因子取值表
B3: 项目名称：时序数据采集与应用管理系统 | I3: 序号 | J3: 类型 | N3: 因子取值
B4: 功能点计数 | I4: 1 | J4: 规模调整 | K4: 规模变更因子 | L4: 规模变更因子 | M4: 项目中期 | N4: 1.21
B5: 功能点计数项（个） | C5: 内部逻辑文件 | D5: 外部接口文件 | E5: 外部输入 | F5: 外部输出 | G5: 外部查询 | I5: 2 | K5: 非功能性特征调整因子 | L5: 分布式处理 | M5: 在多个服务器及处理器上同时相互执行计算机系统中的处理功能 | N5: 1
C6: （ILF） | D6: （EIF） | E6: （EI） | F6: （EO） | G6: （EQ） | I6: 3 | L6: 性能 | M6: 应答时间或处理率对高峰时间或所有业务时间都很重要，对连动系统结束处理时间有限制 | N6: 0
C7: =COUNTIFS(功能点测算明细!H:H,"ILF") | D7: =COUNTIFS(功能点测算明细!H:H,"EIF") | E7: =COUNTIFS(功能点测算明细!H:H,"EI") | F7: =COUNTIFS(功能点测算明细!H:H,"EO") | G7: =COUNTIFS(功能点测算明细!H:H,"EQ") | I7: 4 | L7: 可靠性 | M7: 发生故障时可轻易修复，带来一定不便或经济损失 | N7: 0
B8: 未调整功能点数（功能点） | C8: 估算结果 | E8: 计算公式 | I8: 5 | L8: 多重站点 | M8: 在用途类似的硬件或软件环境下运行 | N8: 0
C9: =10*C7+7*D7+E7*4+F7*5+G7*4 | E9: 估算功能点法：10×ILF+7×EIF+4×EI+5×EO+4×EQ | I9: 6 | L9: 小计 | M9: （分布式处理因子 + 性能因子 + 可靠性因子 + 多重站点因子）×0.025 + 1 | N9: 1.025
B10: 修改类型和复用程度调整 | I10: 7 | J10: 开发功能点单价（元/功能点） | M10: 开发功能点单价上限值为 2348 元/功能点（含税价），按照上限值的 75.53%计取 | N10: 1773.33
B11: 未调整软件规模（功能点） | C11: 估算结果 | E11: 计算公式 | I11: 8 | J11: 业务类型调整因子 | M11: 生产运行I类（跨业务领域系统，如智能运营中心等） | N11: 1
C12: =功能点测算明细!D4 | E12: 未调整功能点数×修改类型调整因子×复用程度调整因子
B13: 规模调整
B14: 规模变更因子 | C14: 1.21 | E14: 根据规模估算阶段取值
B15: 非功能性特征调整因子 | C15: 1.025 | E15: 根据质量特性取值
B16: 软件规模（功能点） | C16: 估算结果 | E16: 计算公式
C17: =C12*1.21*1.025 | E17: 未调整软件规模×规模变更因子×非功能性特征调整因子
B18: 费用估算
B19: 开发功能点单价 （元/功能点） | C19: 1773.33 | E19: 开发功能点单价
B20: 业务类型调整因子 | C20: 1 | E20: 根据业务类型取值
B21: 软件定制开发费用 （万元） | C21: 估算结果 | E21: 计算公式
C22: =C17*C19*C20/10000 | E22: 软件规模×开发功能点单价×业务类型调整因子/10000 | H22: 725.04 | I22: =H22/C19/C15/C14 | J22: 3296.57

Sheet 功能点测算明细
B1: 时序数据采集与应用管理系统项目费用估算
B2: 规模估算方法 | D2: 估算功能点
B3: 未调整功能点数合计 | D3: =SUM(I:I) | P3: =P4-D4 | S3: =D4-S4
B4: 未调整软件规模合计 | D4: =SUM(N:N) | P4: 3296.57 | Q4: 3296.56 | R4: 3296.58 | S4: 3296.59
B5: 编号 | C5: 一级模块 | D5: 二级模块 | E5: 三级模块 | F5: 功能项 | G5: 功能项描述 | H5: 类别 | I5: UFP | J5: 重用程度 | L5: 修改类型 | N5: US | O5: 备注
B6: 1 | C6: 时序数据采集增强中间件与基础平台服务 | D6: 全局参数管理 | E6: 采集频率参数管理 | F6: 作业区频率差异化 | G6: 提供按作业区粒度差异化配置采集频率的技术服务 | H6: ILF | I6: =IF(H6="ILF",10,IF(H6="EIF",7,IF(H6="EI",4,IF(H6="EO",5,IF(H6="EQ",4,""))))) | J6: 低 | K6: =IF(J6="高",0.33,IF(J6="中",0.67,IF(J6="低",1,""))) | L6: 新增 | M6: =IF(L6="新增",1,IF(L6="修改",0.8,IF(L6="删除",0.2,""))) | N6: =I6*K6*M6
B7: 2 | C7: 时序数据采集增强中间件与基础平台服务 | D7: 全局参数管理 | E7: 采集频率参数管理 | F7: 异常加密调整 | G7: 提供异常工况下采集频率从10分钟自动加密至秒级的技术服务 | H7: ILF | I7: =IF(H7="ILF",10,IF(H7="EIF",7,IF(H7="EI",4,IF(H7="EO",5,IF(H7="EQ",4,""))))) | J7: 低 | K7: =IF(J7="高",0.33,IF(J7="中",0.67,IF(J7="低",1,""))) | L7: 新增 | M7: =IF(L7="新增",1,IF(L7="修改",0.8,IF(L7="删除",0.2,""))) | N7: =I7*K7*M7
B8: 3 | C8: 时序数据采集增强中间件与基础平台服务 | D8: 全局参数管理 | E8: 采集频率参数管理 | F8: 低峰降频调整 | G8: 提供夜间低产时段采集频率自动降频的技术服务 | H8: ILF | I8: =IF(H8="ILF",10,IF(H8="EIF",7,IF(H8="EI",4,IF(H8="EO",5,IF(H8="EQ",4,""))))) | J8: 低 | K8: =IF(J8="高",0.33,IF(J8="中",0.67,IF(J8="低",1,""))) | L8: 新增 | M8: =IF(L8="新增",1,IF(L8="修改",0.8,IF(L8="删除",0.2,""))) | N8: =I8*K8*M8
B9: 4 | C9: 时序数据采集增强中间件与基础平台服务 | D9: 全局参数管理 | E9: 采集频率参数管理 | F9: 弱网退避调整 | G9: 提供弱网环境下采集频率按丢包率倍频退避的技术服务 | H9: ILF | I9: =IF(H9="ILF",10,IF(H9="EIF",7,IF(H9="EI",4,IF(H9="EO",5,IF(H9="EQ",4,""))))) | J9: 低 | K9: =IF(J9="高",0.33,IF(J9="中",0.67,IF(J9="低",1,""))) | L9: 新增 | M9: =IF(L9="新增",1,IF(L9="修改",0.8,IF(L9="删除",0.2,""))) | N9: =I9*K9*M9
B10: 5 | C10: 时序数据采集增强中间件与基础平台服务 | D10: 全局参数管理 | E10: 采集频率参数管理 | F10: 频率热加载 | G10: 提供采集频率参数变更后即时热加载生效的技术服务 | H10: ILF | I10: =IF(H10="ILF",10,IF(H10="EIF",7,IF(H10="EI",4,IF(H10="EO",5,IF(H10="EQ",4,""))))) | J10: 低 | K10: =IF(J10="高",0.33,IF(J10="中",0.67,IF(J10="低",1,""))) | L10: 新增 | M10: =IF(L10="新增",1,IF(L10="修改",0.8,IF(L10="删除",0.2,""))) | N10: =I10*K10*M10
B11: 6 | C11: 时序数据采集增强中间件与基础平台服务 | D11: 全局参数管理 | E11: 采集频率参数管理 | F11: 频率版本回滚 | G11: 提供采集频率参数版本回滚操作的技术服务 | H11: ILF | I11: =IF(H11="ILF",10,IF(H11="EIF",7,IF(H11="EI",4,IF(H11="EO",5,IF(H11="EQ",4,""))))) | J11: 低 | K11: =IF(J11="高",0.33,IF(J11="中",0.67,IF(J11="低",1,""))) | L11: 新增 | M11: =IF(L11="新增",1,IF(L11="修改",0.8,IF(L11="删除",0.2,""))) | N11: =I11*K11*M11
B12: 7 | C12: 时序数据采集增强中间件与基础平台服务 | D12: 全局参数管理 | E12: 采集频率参数管理 | F12: 频率变更审计 | G12: 提供采集频率参数变更的审计追踪技术服务 | H12: ILF | I12: =IF(H12="ILF",10,IF(H12="EIF",7,IF(H12="EI",4,IF(H12="EO",5,IF(H12="EQ",4,""))))) | J12: 中 | K12: =IF(J12="高",0.33,IF(J12="中",0.67,IF(J12="低",1,""))) | L12: 新增 | M12: =IF(L12="新增",1,IF(L12="修改",0.8,IF(L12="删除",0.2,""))) | N12: =I12*K12*M12
B13: 8 | C13: 时序数据采集增强中间件与基础平台服务 | D13: 全局参数管理 | E13: 采集频率参数管理 | F13: 频率配置导出 | G13: 提供采集频率配置批量导出Excel的技术服务 | H13: ILF | I13: =IF(H13="ILF",10,IF(H13="EIF",7,IF(H13="EI",4,IF(H13="EO",5,IF(H13="EQ",4,""))))) | J13: 中 | K13: =IF(J13="高",0.33,IF(J13="中",0.67,IF(J13="低",1,""))) | L13: 新增 | M13: =IF(L13="新增",1,IF(L13="修改",0.8,IF(L13="删除",0.2,""))) | N13: =I13*K13*M13
B14: 9 | C14: 时序数据采集增强中间件与基础平台服务 | D14: 全局参数管理 | E14: 采集频率参数管理 | F14: 频率配置导入 | G14: 提供采集频率配置批量导入的技术服务 | H14: ILF | I14: =IF(H14="ILF",10,IF(H14="EIF",7,IF(H14="EI",4,IF(H14="EO",5,IF(H14="EQ",4,""))))) | J14: 中 | K14: =IF(J14="高",0.33,IF(J14="中",0.67,IF(J14="低",1,""))) | L14: 新增 | M14: =IF(L14="新增",1,IF(L14="修改",0.8,IF(L14="删除",0.2,""))) | N14: =I14*K14*M14
B15: 10 | C15: 时序数据采集增强中间件与基础平台服务 | D15: 全局参数管理 | E15: 采集频率参数管理 | F15: 频率配置对比 | G15: 提供采集频率配置版本间差异对比的技术服务 | H15: ILF | I15: =IF(H15="ILF",10,IF(H15="EIF",7,IF(H15="EI",4,IF(H15="EO",5,IF(H15="EQ",4,""))))) | J15: 中 | K15: =IF(J15="高",0.33,IF(J15="中",0.67,IF(J15="低",1,""))) | L15: 新增 | M15: =IF(L15="新增",1,IF(L15="修改",0.8,IF(L15="删除",0.2,""))) | N15: =I15*K15*M15
B16: 11 | C16: 时序数据采集增强中间件与基础平台服务 | D16: 全局参数管理 | E16: 采集频率参数管理 | F16: 采集窗口配置 | G16: 提供采集时间窗口和错峰调度时隙参数配置服务 | H16: ILF | I16: =IF(H16="ILF",10,IF(H16="EIF",7,IF(H16="EI",4,IF(H16="EO",5,IF(H16="EQ",4,""))))) | J16: 中 | K16: =IF(J16="高",0.33,IF(J16="中",0.67,IF(J16="低",1,""))) | L16: 新增 | M16: =IF(L16="新增",1,IF(L16="修改",0.8,IF(L16="删除",0.2,""))) | N16: =I16*K16*M16
B17: 12 | C17: 时序数据采集增强中间件与基础平台服务 | D17: 全局参数管理 | E17: 采集频率参数管理 | F17: 休眠时段配置 | G17: 提供设备休眠时段和唤醒时间的参数配置服务 | H17: ILF | I17: =IF(H17="ILF",10,IF(H17="EIF",7,IF(H17="EI",4,IF(H17="EO",5,IF(H17="EQ",4,""))))) | J17: 中 | K17: =IF(J17="高",0.33,IF(J17="中",0.67,IF(J17="低",1,""))) | L17: 新增 | M17: =IF(L17="新增",1,IF(L17="修改",0.8,IF(L17="删除",0.2,""))) | N17: =I17*K17*M17
... B847: 842 | C847: 高频时序数据全链路压力测试与性能验证服务 | D847: 虚拟设备模拟 | E847: 场景配置 | F847: 多站点并发 | G847: 提供多作业区同时并发采集模拟服务 | H847: EQ | I847: =IF(H847="ILF",10,IF(H847="EIF",7,IF(H847="EI",4,IF(H847="EO",5,IF(H847="EQ",4,""))))) | J847: 高 | K847: =IF(J847="高",0.33,IF(J847="中",0.67,IF(J847="低",1,""))) | L847: 新增 | M847: =IF(L847="新增",1,IF(L847="修改",0.8,IF(L847="删除",0.2,""))) | N847: =I847*K847*M847
